anss/__init__.py
anss/admin.py
anss/apps.py
anss/models.py
anss/tests.py
anss/urls.py
anss/views.py
anss/management/__init__.py
anss/management/commands/__init__.py
anss/management/commands/getlatestanssfeed.py
anss/migrations/0001_initial.py
anss/migrations/0002_auto_20190709_0830.py
anss/migrations/0003_auto_20190709_0939.py
anss/migrations/0004_auto_20190709_0943.py
anss/migrations/0005_auto_20190709_1035.py
anss/migrations/0006_auto_20190709_1147.py
anss/migrations/__init__.py
django_anss_archive-0.1.1.dist-info/LICENSE
django_anss_archive-0.1.1.dist-info/METADATA
django_anss_archive-0.1.1.dist-info/WHEEL
django_anss_archive-0.1.1.dist-info/top_level.txt
django_anss_archive-0.1.1.dist-info/RECORD
