Metadata-Version: 2.1
Name: django-anss-archive
Version: 0.1.1
Summary: A Django application to archive real-time earthquake notifications from the USGS's Advanced National Seismic System
Home-page: https://palewi.re/docs/django-anss-archive/
Author: Ben Welsh
Author-email: b@palewi.re
License: MIT
Project-URL: Maintainer, https://github.com/palewire
Project-URL: Source, https://github.com/palewire/django-anss-archive
Project-URL: Tracker, https://github.com/palewire/django-anss-archive/issues
Classifier: Development Status :: 5 - Production/Stable
Classifier: Programming Language :: Python
Classifier: Programming Language :: Python :: 3
Classifier: Programming Language :: Python :: 3.8
Classifier: Programming Language :: Python :: 3.9
Classifier: Programming Language :: Python :: 3.10
Classifier: License :: OSI Approved :: MIT License
License-File: LICENSE
Requires-Dist: requests
